mongodb_connect/__init__.py
mongodb_connect/mongo_crud.py
mongodb_connect_ha-0.0.1.dist-info/METADATA
mongodb_connect_ha-0.0.1.dist-info/WHEEL
mongodb_connect_ha-0.0.1.dist-info/top_level.txt
mongodb_connect_ha-0.0.1.dist-info/RECORD
